repin/__init__.py
repin/apis.py
repin/cache.py
repin/cli.py
repin/cli_args.py
repin/collectors.py
repin/config.py
repin/errors.py
repin/filters.py
repin/helpers.py
repin/log.py
repin/utils.py
repin-0.4.0.dist-info/METADATA
repin-0.4.0.dist-info/WHEEL
repin-0.4.0.dist-info/entry_points.txt
repin-0.4.0.dist-info/top_level.txt
repin-0.4.0.dist-info/RECORD
