Metadata-Version: 2.1
Name: repin
Version: 0.4.0
Summary: Repository Inspector
Home-page: https://github.com/inessa13/repin
Author: David Jhanyan aka inessa13
Author-email: davo.fastcall@gmail.com
License: MIT
Platform: Development Status :: 4 - Beta
Platform: Programming Language :: Python
Platform: Programming Language :: Python :: 3
Platform: Programming Language :: Python :: 3.6
Platform: Programming Language :: Python :: 3.7
Platform: Topic :: Software Development
Platform: Topic :: Utilities
Requires-Python: >=3.0
Requires-Dist: mock
Requires-Dist: python-gitlab (==1.5.1)
Requires-Dist: python-Levenshtein (==0.12.0)
Requires-Dist: PyYAML
Requires-Dist: toml
Provides-Extra: tests
Requires-Dist: pytest ; extra == 'tests'
Requires-Dist: coverage ; extra == 'tests'
